apibook-0.1.2.dist-info/METADATA
apibook-0.1.2.dist-info/WHEEL
apibook-0.1.2.dist-info/entry_points.txt
apibook-0.1.2.dist-info/licenses/LICENSE-MIT.txt
apibook/__init__.py
apibook/_ast.py
apibook/cli.py
apibook/data.py
apibook/main.py
apibook-0.1.2.dist-info/RECORD
