Metadata-Version: 2.1
Name: apibook
Version: 0.1.2
Summary: API documentation generator for MdBook
Keywords: mdbook apidoc documentation markdown
Author-Email: Tom Solberg <me@sbg.dev>
License: MIT License
Classifier: Development Status :: 4 - Beta
Classifier: Programming Language :: Python
Classifier: Topic :: Software Development :: Documentation
Classifier: Topic :: Text Processing :: Markup :: Markdown
Project-URL: Repository, https://github.com/tgolsson/python-apibook
Project-URL: Changelog, https://github.com/tgolsson/python-apibook/tree/main/CHANGELOG.md
Requires-Python: >=3.9
Requires-Dist: docstring_parser
Requires-Dist: rich
